prenlp/__init__.py
prenlp/data/__init__.py
prenlp/data/normalizer.py
prenlp/data/utils.py
prenlp/data/dataset/__init__.py
prenlp/data/dataset/base.py
prenlp/data/dataset/language_modeling.py
prenlp/data/dataset/sentiment.py
prenlp/tokenizer/__init__.py
prenlp/tokenizer/tokenizer.py
prenlp/utils/__init__.py
prenlp-0.0.13.dist-info/LICENSE
prenlp-0.0.13.dist-info/METADATA
prenlp-0.0.13.dist-info/WHEEL
prenlp-0.0.13.dist-info/top_level.txt
prenlp-0.0.13.dist-info/RECORD
