Metadata-Version: 2.1
Name: prenlp
Version: 0.0.13
Summary: Preprocessing Library for Natural Language Processing
Home-page: https://github.com/lyeoni/prenlp
Author: Hoyeon Lee
Author-email: lyeoni.g@gmail.com
License: UNKNOWN
Keywords: nlp,text-preprocessing
Platform: UNKNOWN
Classifier: Programming Language :: Python :: 3.6
Classifier: Programming Language :: Python :: 3.7
Classifier: License :: OSI Approved :: Apache Software License
Requires-Dist: nltk (==3.2.5)
Requires-Dist: konlpy
Requires-Dist: sentencepiece
Requires-Dist: ijson
Requires-Dist: py7zr (==0.5b5)
